ghp_import.py
ghp_import-2.0.1.dist-info/LICENSE
ghp_import-2.0.1.dist-info/METADATA
ghp_import-2.0.1.dist-info/WHEEL
ghp_import-2.0.1.dist-info/entry_points.txt
ghp_import-2.0.1.dist-info/top_level.txt
ghp_import-2.0.1.dist-info/RECORD
