Metadata-Version: 2.1
Name: ghp-import
Version: 2.0.1
Summary: Copy your docs directly to the gh-pages branch.
Home-page: https://github.com/c-w/ghp-import
Author: Paul Joseph Davis
Author-email: paul.joseph.davis@gmail.com
License: Apache Software License
Platform: UNKNOWN
Classifier: Development Status :: 5 - Production/Stable
Classifier: License :: OSI Approved :: Apache Software License
Classifier: Intended Audience :: Developers
Classifier: Natural Language :: English
Classifier: Operating System :: OS Independent
Classifier: Programming Language :: Python
Classifier: Programming Language :: Python :: 2
Classifier: Programming Language :: Python :: 3
License-File: LICENSE
Requires-Dist: python-dateutil (>=2.8.1)
Provides-Extra: dev
Requires-Dist: twine ; extra == 'dev'
Requires-Dist: markdown ; extra == 'dev'
Requires-Dist: flake8 ; extra == 'dev'
Requires-Dist: wheel ; extra == 'dev'
